{
  "products": [
    {
      "name": "Simple belt",
      "photo": "/img/belt.jpg",
      "variants": [
        {
          "color": "#000000",
          "price": "100",
          "photo": "/img/belt.jpg",
          "isSelected": true
        },
        {
          "color": "#000000",
          "price": "200",
          "photo": "/img/belt.jpg",
          "isSelected": false
        },
        {
          "color": "#000000",
          "price": "200",
          "photo": "/img/belt.jpg",
          "isSelected": false
        },
        {
          "color": "#000000",
          "price": "200",
          "photo": "/img/belt.jpg",
          "isSelected": false
        }
      ]
    },
    {
      "name": "Simple wallet",
      "photo": "/img/wallet.jpg",
      "variants": [
        {
          "color": "#000000",
          "price": "70",
          "photo": "/img/belt.jpg",
          "isSelected": false
        },
        {
          "color": "#000000",
          "price": "200",
          "photo": "/img/belt.jpg",
          "isSelected": true
        },
        {
          "color": "#000000",
          "price": "200",
          "photo": "/img/belt.jpg",
          "isSelected": false
        },
        {
          "color": "#000000",
          "price": "200",
          "photo": "/img/belt.jpg",
          "isSelected": false
        }
  ]
    },
    {
      "name": "Simple bag",
      "photo": "/img/bag.jpg",
      "variants": [
        {
          "color": "#000000",
          "price": "150",
          "photo": "/img/belt.jpg",
          "isSelected": false
        },
        {
          "color": "#000000",
          "price": "200",
          "photo": "/img/belt.jpg",
          "isSelected": false
        },
        {
          "color": "#000000",
          "price": "200",
          "photo": "/img/belt.jpg",
          "isSelected": false
        },
        {
          "color": "#000000",
          "price": "200",
          "photo": "/img/belt.jpg",
          "isSelected": true
        }
      ]
    }
  ]
}